pycortexintelligence/__init__.py
pycortexintelligence/functions.py
pycortexintelligence/core/__init__.py
pycortexintelligence/core/config.py
pycortexintelligence/core/funcs_env.py
pycortexintelligence/core/funcs_mail.py
pycortexintelligence/core/funcs_startproject.py
pycortexintelligence/core/messages.py
pycortexintelligence-1.2.7.data/scripts/cortex.py
pycortexintelligence-1.2.7.dist-info/LICENSE
pycortexintelligence-1.2.7.dist-info/METADATA
pycortexintelligence-1.2.7.dist-info/WHEEL
pycortexintelligence-1.2.7.dist-info/top_level.txt
pycortexintelligence-1.2.7.dist-info/RECORD
