Metadata-Version: 2.1
Name: pycortexintelligence
Version: 1.2.7
Summary: Cortex Intelligence Platform Python SDK
Home-page: https://github.com/cortex-intelligence/pycortexintelligence
Author: Enderson Menezes
Author-email: data.integrations@cortex-intelligence.com
Classifier: Programming Language :: Python :: 3
Classifier: License :: OSI Approved :: MIT License
Classifier: Operating System :: OS Independent
Requires-Python: >=3.7
License-File: LICENSE
Requires-Dist: requests >=2.25.0
Requires-Dist: click >=7.1.2
Requires-Dist: boto3 >=1.21.32
Requires-Dist: pandas <2.0.0,>=1.3.5
